{"file":"stand_3.png","frames":{"idle0000":{"x":1275,"y":2,"w":159,"h":219,"offX":146,"offY":46,"sourceW":399,"sourceH":399},"idle0002":{"x":937,"y":2,"w":167,"h":219,"offX":138,"offY":39,"sourceW":399,"sourceH":399},"idle0004":{"x":760,"y":2,"w":175,"h":217,"offX":130,"offY":34,"sourceW":399,"sourceH":399},"idle0006":{"x":396,"y":2,"w":183,"h":217,"offX":123,"offY":29,"sourceW":399,"sourceH":399},"idle0008":{"x":2,"y":2,"w":193,"h":215,"offX":114,"offY":27,"sourceW":399,"sourceH":399},"idle0010":{"x":197,"y":2,"w":197,"h":211,"offX":111,"offY":29,"sourceW":399,"sourceH":399},"idle0012":{"x":2,"y":219,"w":193,"h":213,"offX":116,"offY":32,"sourceW":399,"sourceH":399},"idle0014":{"x":197,"y":215,"w":185,"h":219,"offX":124,"offY":35,"sourceW":399,"sourceH":399},"idle0016":{"x":581,"y":2,"w":177,"h":219,"offX":133,"offY":43,"sourceW":399,"sourceH":399},"idle0018":{"x":1106,"y":2,"w":167,"h":217,"offX":143,"offY":52,"sourceW":399,"sourceH":399},"idle0020":{"x":1436,"y":2,"w":163,"h":213,"offX":147,"offY":62,"sourceW":399,"sourceH":399},"idle0022":{"x":543,"y":223,"w":161,"h":207,"offX":149,"offY":74,"sourceW":399,"sourceH":399},"idle0024":{"x":1177,"y":223,"w":159,"h":201,"offX":151,"offY":85,"sourceW":399,"sourceH":399},"idle0026":{"x":1497,"y":219,"w":157,"h":193,"offX":152,"offY":95,"sourceW":399,"sourceH":399},"idle0028":{"x":1656,"y":219,"w":157,"h":191,"offX":151,"offY":97,"sourceW":399,"sourceH":399},"idle0030":{"x":1338,"y":223,"w":157,"h":197,"offX":151,"offY":90,"sourceW":399,"sourceH":399},"idle0032":{"x":1020,"y":223,"w":155,"h":203,"offX":152,"offY":81,"sourceW":399,"sourceH":399},"idle0034":{"x":863,"y":223,"w":155,"h":209,"offX":151,"offY":73,"sourceW":399,"sourceH":399},"idle0036":{"x":706,"y":223,"w":155,"h":209,"offX":150,"offY":69,"sourceW":399,"sourceH":399},"idle0038":{"x":384,"y":221,"w":157,"h":213,"offX":148,"offY":61,"sourceW":399,"sourceH":399},"idle0040":{"x":1601,"y":2,"w":159,"h":215,"offX":146,"offY":52,"sourceW":399,"sourceH":399}}}