{"width":512,"SubTexture":[{"frameWidth":84,"y":128,"frameHeight":137,"width":49,"frameX":-18,"height":122,"name":"cz_00016","frameY":-14,"x":459},{"frameWidth":84,"y":381,"frameHeight":137,"width":54,"frameX":-16,"height":124,"name":"cz_00013","frameY":-12,"x":403},{"frameWidth":84,"y":291,"frameHeight":137,"width":53,"frameX":-16,"height":132,"name":"cz_00003","frameY":-4,"x":56},{"frameWidth":84,"y":130,"frameHeight":137,"width":55,"frameX":-17,"height":126,"name":"cz_00006","frameY":-9,"x":235},{"frameWidth":84,"y":252,"frameHeight":137,"width":53,"frameX":-15,"height":127,"name":"cz_00022","frameY":-9,"x":403},{"frameWidth":84,"y":291,"frameHeight":137,"width":55,"frameX":-17,"height":127,"name":"cz_00008","frameY":-8,"x":111},{"frameWidth":84,"y":255,"frameHeight":137,"width":53,"frameX":-15,"height":128,"name":"cz_00023","frameY":-8,"x":348},{"frameWidth":84,"y":1,"frameHeight":137,"width":55,"frameX":-16,"height":127,"name":"cz_00005","frameY":-8,"x":179},{"frameWidth":84,"y":1,"frameHeight":137,"width":49,"frameX":-17,"height":123,"name":"cz_00017","frameY":-13,"x":406},{"frameWidth":84,"y":130,"frameHeight":137,"width":54,"frameX":-16,"height":129,"name":"cz_00004","frameY":-7,"x":179},{"frameWidth":84,"y":128,"frameHeight":137,"width":51,"frameX":-16,"height":122,"name":"cz_00020","frameY":-13,"x":406},{"frameWidth":84,"y":128,"frameHeight":137,"width":55,"frameX":-17,"height":125,"name":"cz_00007","frameY":-10,"x":292},{"frameWidth":84,"y":1,"frameHeight":137,"width":49,"frameX":-17,"height":121,"name":"cz_00018","frameY":-14,"x":350},{"frameWidth":84,"y":385,"frameHeight":137,"width":53,"frameX":-16,"height":124,"name":"cz_00014","frameY":-12,"x":348},{"frameWidth":84,"y":291,"frameHeight":137,"width":53,"frameX":-16,"height":133,"name":"cz_00002","frameY":-3,"x":1},{"frameWidth":84,"y":1,"frameHeight":137,"width":55,"frameX":-17,"height":125,"name":"cz_00010","frameY":-10,"x":236},{"frameWidth":84,"y":291,"frameHeight":137,"width":55,"frameX":-17,"height":127,"name":"cz_00009","frameY":-8,"x":168},{"frameWidth":84,"y":127,"frameHeight":137,"width":55,"frameX":-16,"height":123,"name":"cz_00012","frameY":-12,"x":349},{"frameWidth":84,"y":1,"frameHeight":137,"width":51,"frameX":-17,"height":125,"name":"cz_00015","frameY":-11,"x":458},{"frameWidth":84,"y":255,"frameHeight":137,"width":53,"frameX":-16,"height":129,"name":"cz_00000","frameY":-7,"x":293},{"frameWidth":84,"y":1,"frameHeight":137,"width":55,"frameX":-16,"height":124,"name":"cz_00011","frameY":-11,"x":293},{"frameWidth":84,"y":252,"frameHeight":137,"width":51,"frameX":-16,"height":119,"name":"cz_00019","frameY":-16,"x":458},{"frameWidth":84,"y":386,"frameHeight":137,"width":52,"frameX":-15,"height":125,"name":"cz_00021","frameY":-11,"x":280},{"frameWidth":84,"y":261,"frameHeight":137,"width":53,"frameX":-16,"height":131,"name":"cz_00001","frameY":-5,"x":225},{"width":176,"y":1,"height":288,"name":"elingchuanzhang/图层_728_拷贝","x":1}],"height":512,"name":"hero_752_1","imagePath":"hero_752_1_tex.png"}