{"width":512,"imagePath":"hero_701_2_tex.png","SubTexture":[{"width":255,"y":1,"height":127,"name":"elingchuanzhang/dao","x":1},{"width":68,"y":1,"height":114,"name":"elingchuanzhang/baixiu","x":258},{"frameY":-12,"y":255,"frameWidth":84,"frameHeight":137,"width":54,"height":124,"name":"cz_00013","frameX":-16,"x":168},{"frameY":-5,"y":130,"frameWidth":84,"frameHeight":137,"width":53,"height":131,"name":"cz_00001","frameX":-16,"x":440},{"frameY":-14,"y":386,"frameWidth":84,"frameHeight":137,"width":49,"height":121,"name":"cz_00018","frameX":-17,"x":112},{"frameY":-10,"y":263,"frameWidth":84,"frameHeight":137,"width":55,"height":125,"name":"cz_00010","frameX":-17,"x":426},{"frameY":-11,"y":257,"frameWidth":84,"frameHeight":137,"width":55,"height":124,"name":"cz_00011","frameX":-16,"x":1},{"frameY":-7,"y":130,"frameWidth":84,"frameHeight":137,"width":53,"height":129,"name":"cz_00000","frameX":-16,"x":58},{"frameY":-11,"y":381,"frameWidth":84,"frameHeight":137,"width":52,"height":125,"name":"cz_00021","frameX":-15,"x":58},{"frameY":-13,"y":267,"frameWidth":84,"frameHeight":137,"width":51,"height":122,"name":"cz_00020","frameX":-16,"x":280},{"frameY":-12,"y":130,"frameWidth":84,"frameHeight":137,"width":55,"height":123,"name":"cz_00012","frameX":-16,"x":168},{"frameY":-8,"y":1,"frameWidth":84,"frameHeight":137,"width":55,"height":127,"name":"cz_00009","frameX":-17,"x":440},{"frameY":-3,"y":1,"frameWidth":84,"frameHeight":137,"width":53,"height":133,"name":"cz_00002","frameX":-16,"x":328},{"frameY":-16,"y":380,"frameWidth":84,"frameHeight":137,"width":51,"height":119,"name":"cz_00019","frameX":-16,"x":224},{"frameY":-9,"y":251,"frameWidth":84,"frameHeight":137,"width":53,"height":127,"name":"cz_00022","frameX":-15,"x":225},{"frameY":-8,"y":130,"frameWidth":84,"frameHeight":137,"width":53,"height":128,"name":"cz_00023","frameX":-15,"x":113},{"frameY":-12,"y":260,"frameWidth":84,"frameHeight":137,"width":53,"height":124,"name":"cz_00014","frameX":-16,"x":113},{"frameY":-10,"y":130,"frameWidth":84,"frameHeight":137,"width":55,"height":125,"name":"cz_00007","frameX":-17,"x":1},{"frameY":-7,"y":136,"frameWidth":84,"frameHeight":137,"width":54,"height":129,"name":"cz_00004","frameX":-16,"x":313},{"frameY":-13,"y":501,"frameWidth":84,"frameHeight":137,"width":49,"height":123,"name":"cz_00017","frameX":-17,"x":224},{"frameY":-8,"y":130,"frameWidth":84,"frameHeight":137,"width":55,"height":127,"name":"cz_00005","frameX":-16,"x":383},{"frameY":-9,"y":259,"frameWidth":84,"frameHeight":137,"width":55,"height":126,"name":"cz_00006","frameX":-17,"x":369},{"frameY":-11,"y":383,"frameWidth":84,"frameHeight":137,"width":51,"height":125,"name":"cz_00015","frameX":-17,"x":1},{"frameY":-14,"y":381,"frameWidth":84,"frameHeight":137,"width":49,"height":122,"name":"cz_00016","frameX":-18,"x":168},{"frameY":-4,"y":117,"frameWidth":84,"frameHeight":137,"width":53,"height":132,"name":"cz_00003","frameX":-16,"x":258},{"frameY":-8,"y":1,"frameWidth":84,"frameHeight":137,"width":55,"height":127,"name":"cz_00008","frameX":-17,"x":383}],"height":1024,"name":"hero_701_2"}