{"file":"boom.png","frames":{"4_00":{"x":0,"y":0,"w":1,"h":1,"offX":0,"offY":0,"sourceW":640,"sourceH":800},"4_11":{"x":1,"y":0,"w":18,"h":80,"offX":520,"offY":399,"sourceW":640,"sourceH":800},"4_01":{"x":19,"y":0,"w":142,"h":142,"offX":251,"offY":331,"sourceW":640,"sourceH":800},"4_02":{"x":161,"y":0,"w":342,"h":344,"offX":149,"offY":231,"sourceW":640,"sourceH":800},"4_10":{"x":503,"y":0,"w":422,"h":388,"offX":113,"offY":187,"sourceW":640,"sourceH":800},"4_09":{"x":925,"y":0,"w":430,"h":422,"offX":114,"offY":180,"sourceW":640,"sourceH":800},"4_08":{"x":0,"y":422,"w":450,"h":440,"offX":99,"offY":176,"sourceW":640,"sourceH":800},"4_07":{"x":450,"y":422,"w":468,"h":468,"offX":80,"offY":177,"sourceW":640,"sourceH":800},"4_06":{"x":918,"y":422,"w":518,"h":498,"offX":71,"offY":157,"sourceW":640,"sourceH":800},"4_05":{"x":0,"y":920,"w":524,"h":536,"offX":65,"offY":132,"sourceW":640,"sourceH":800},"4_04":{"x":524,"y":920,"w":534,"h":540,"offX":59,"offY":131,"sourceW":640,"sourceH":800},"4_03":{"x":1058,"y":920,"w":542,"h":512,"offX":74,"offY":149,"sourceW":640,"sourceH":800}}}