{"file":"start.png","frames":{"lanse1_00000":{"x":2,"y":1646,"w":334,"h":238,"offX":192,"offY":369,"sourceW":700,"sourceH":700},"lanse1_00001":{"x":1152,"y":2,"w":522,"h":392,"offX":99,"offY":272,"sourceW":700,"sourceH":700},"lanse1_00002":{"x":2,"y":584,"w":694,"h":506,"offX":6,"offY":194,"sourceW":700,"sourceH":700},"lanse1_00003":{"x":2,"y":2,"w":694,"h":580,"offX":6,"offY":120,"sourceW":700,"sourceH":700},"lanse1_00004":{"x":2,"y":1092,"w":430,"h":552,"offX":143,"offY":41,"sourceW":700,"sourceH":700},"lanse1_00005":{"x":698,"y":2,"w":452,"h":550,"offX":128,"offY":40,"sourceW":700,"sourceH":700},"lanse1_00006":{"x":1178,"y":726,"w":470,"h":334,"offX":118,"offY":261,"sourceW":700,"sourceH":700},"lanse1_00007":{"x":698,"y":554,"w":472,"h":338,"offX":121,"offY":264,"sourceW":700,"sourceH":700},"lanse1_00008":{"x":698,"y":894,"w":478,"h":334,"offX":115,"offY":264,"sourceW":700,"sourceH":700},"lanse1_00009":{"x":1172,"y":396,"w":482,"h":328,"offX":113,"offY":261,"sourceW":700,"sourceH":700},"lanse1_00010":{"x":1178,"y":1062,"w":468,"h":320,"offX":125,"offY":262,"sourceW":700,"sourceH":700},"lanse1_00011":{"x":434,"y":1230,"w":468,"h":322,"offX":124,"offY":262,"sourceW":700,"sourceH":700},"lanse1_00012":{"x":434,"y":1554,"w":464,"h":308,"offX":124,"offY":268,"sourceW":700,"sourceH":700},"lanse1_00013":{"x":1152,"y":1384,"w":450,"h":310,"offX":125,"offY":265,"sourceW":700,"sourceH":700},"lanse1_00014":{"x":1676,"y":322,"w":286,"h":314,"offX":215,"offY":266,"sourceW":700,"sourceH":700},"lanse1_00015":{"x":1676,"y":2,"w":290,"h":318,"offX":213,"offY":265,"sourceW":700,"sourceH":700},"lanse1_00016":{"x":1604,"y":1578,"w":294,"h":316,"offX":210,"offY":269,"sourceW":700,"sourceH":700},"lanse1_00017":{"x":1656,"y":638,"w":298,"h":318,"offX":209,"offY":270,"sourceW":700,"sourceH":700},"lanse1_00018":{"x":1650,"y":958,"w":298,"h":308,"offX":208,"offY":281,"sourceW":700,"sourceH":700},"lanse1_00019":{"x":1648,"y":1268,"w":296,"h":308,"offX":207,"offY":278,"sourceW":700,"sourceH":700},"lanse1_00020":{"x":904,"y":1230,"w":246,"h":190,"offX":208,"offY":277,"sourceW":700,"sourceH":700},"lanse1_00021":{"x":904,"y":1422,"w":244,"h":190,"offX":207,"offY":276,"sourceW":700,"sourceH":700},"lanse1_00022":{"x":900,"y":1614,"w":240,"h":188,"offX":207,"offY":274,"sourceW":700,"sourceH":700},"lanse1_00023":{"x":1142,"y":1696,"w":206,"h":144,"offX":238,"offY":274,"sourceW":700,"sourceH":700},"lanse1_00024":{"x":1350,"y":1696,"w":202,"h":140,"offX":239,"offY":275,"sourceW":700,"sourceH":700},"lanse1_00025":{"x":434,"y":1092,"w":200,"h":38,"offX":238,"offY":332,"sourceW":700,"sourceH":700},"lanse1_00026":{"x":900,"y":1804,"w":192,"h":20,"offX":243,"offY":345,"sourceW":700,"sourceH":700}}}