{"file":"2.png","frames":{"daji_00000":{"x":0,"y":0,"w":148,"h":155,"offX":108,"offY":152,"sourceW":360,"sourceH":375},"daji_00001":{"x":148,"y":0,"w":166,"h":209,"offX":102,"offY":109,"sourceW":360,"sourceH":375},"daji_00002":{"x":314,"y":0,"w":188,"h":259,"offX":96,"offY":58,"sourceW":360,"sourceH":375},"daji_00003":{"x":502,"y":0,"w":204,"h":275,"offX":78,"offY":50,"sourceW":360,"sourceH":375},"daji_00004":{"x":706,"y":0,"w":224,"h":287,"offX":63,"offY":46,"sourceW":360,"sourceH":375},"daji_00005":{"x":930,"y":0,"w":208,"h":223,"offX":71,"offY":106,"sourceW":360,"sourceH":375},"daji_00006":{"x":1138,"y":0,"w":202,"h":215,"offX":77,"offY":109,"sourceW":360,"sourceH":375},"daji_00007":{"x":1340,"y":0,"w":188,"h":185,"offX":94,"offY":142,"sourceW":360,"sourceH":375},"daji_00008":{"x":0,"y":287,"w":186,"h":177,"offX":89,"offY":141,"sourceW":360,"sourceH":375},"daji_00009":{"x":186,"y":287,"w":176,"h":177,"offX":90,"offY":139,"sourceW":360,"sourceH":375},"daji_00010":{"x":362,"y":287,"w":176,"h":183,"offX":90,"offY":135,"sourceW":360,"sourceH":375},"daji_00011":{"x":538,"y":287,"w":170,"h":185,"offX":96,"offY":134,"sourceW":360,"sourceH":375},"daji_00012":{"x":708,"y":287,"w":172,"h":185,"offX":94,"offY":135,"sourceW":360,"sourceH":375},"daji_00013":{"x":880,"y":287,"w":174,"h":187,"offX":92,"offY":134,"sourceW":360,"sourceH":375},"daji_00014":{"x":1054,"y":287,"w":176,"h":187,"offX":91,"offY":135,"sourceW":360,"sourceH":375},"daji_00015":{"x":1230,"y":287,"w":178,"h":185,"offX":89,"offY":137,"sourceW":360,"sourceH":375},"daji_00016":{"x":0,"y":474,"w":180,"h":185,"offX":88,"offY":139,"sourceW":360,"sourceH":375},"daji_00017":{"x":180,"y":474,"w":184,"h":191,"offX":86,"offY":134,"sourceW":360,"sourceH":375},"daji_00018":{"x":364,"y":474,"w":186,"h":191,"offX":85,"offY":134,"sourceW":360,"sourceH":375},"daji_00019":{"x":550,"y":474,"w":188,"h":189,"offX":84,"offY":136,"sourceW":360,"sourceH":375},"daji_00020":{"x":738,"y":474,"w":190,"h":181,"offX":83,"offY":145,"sourceW":360,"sourceH":375},"daji_00021":{"x":928,"y":474,"w":194,"h":183,"offX":81,"offY":144,"sourceW":360,"sourceH":375},"daji_00022":{"x":1122,"y":474,"w":196,"h":185,"offX":80,"offY":142,"sourceW":360,"sourceH":375},"daji_00023":{"x":1318,"y":474,"w":194,"h":187,"offX":83,"offY":141,"sourceW":360,"sourceH":375},"daji_00024":{"x":0,"y":665,"w":186,"h":177,"offX":84,"offY":145,"sourceW":360,"sourceH":375},"daji_00025":{"x":186,"y":665,"w":160,"h":175,"offX":97,"offY":145,"sourceW":360,"sourceH":375},"daji_00026":{"x":346,"y":665,"w":132,"h":179,"offX":113,"offY":137,"sourceW":360,"sourceH":375},"daji_00027":{"x":478,"y":665,"w":132,"h":173,"offX":113,"offY":143,"sourceW":360,"sourceH":375},"daji_00028":{"x":610,"y":665,"w":128,"h":173,"offX":113,"offY":143,"sourceW":360,"sourceH":375},"daji_00029":{"x":738,"y":665,"w":126,"h":173,"offX":114,"offY":143,"sourceW":360,"sourceH":375},"daji_00030":{"x":864,"y":665,"w":126,"h":119,"offX":114,"offY":197,"sourceW":360,"sourceH":375},"daji_00031":{"x":990,"y":665,"w":126,"h":119,"offX":114,"offY":197,"sourceW":360,"sourceH":375},"daji_00032":{"x":1116,"y":665,"w":126,"h":119,"offX":114,"offY":197,"sourceW":360,"sourceH":375},"daji_00033":{"x":1242,"y":665,"w":126,"h":119,"offX":114,"offY":197,"sourceW":360,"sourceH":375},"daji_00034":{"x":1368,"y":665,"w":126,"h":91,"offX":114,"offY":225,"sourceW":360,"sourceH":375},"daji_00035":{"x":0,"y":844,"w":126,"h":91,"offX":114,"offY":225,"sourceW":360,"sourceH":375},"daji_00036":{"x":126,"y":844,"w":124,"h":77,"offX":115,"offY":239,"sourceW":360,"sourceH":375},"daji_00037":{"x":250,"y":844,"w":124,"h":77,"offX":115,"offY":239,"sourceW":360,"sourceH":375},"daji_00038":{"x":374,"y":844,"w":124,"h":77,"offX":115,"offY":239,"sourceW":360,"sourceH":375},"daji_00039":{"x":498,"y":844,"w":124,"h":71,"offX":115,"offY":241,"sourceW":360,"sourceH":375},"daji_00040":{"x":622,"y":844,"w":124,"h":71,"offX":115,"offY":241,"sourceW":360,"sourceH":375},"daji_00041":{"x":746,"y":844,"w":124,"h":71,"offX":115,"offY":241,"sourceW":360,"sourceH":375},"daji_00042":{"x":870,"y":844,"w":124,"h":71,"offX":115,"offY":241,"sourceW":360,"sourceH":375},"daji_00043":{"x":994,"y":844,"w":124,"h":71,"offX":115,"offY":241,"sourceW":360,"sourceH":375},"daji_00044":{"x":1118,"y":844,"w":124,"h":69,"offX":115,"offY":243,"sourceW":360,"sourceH":375},"daji_00045":{"x":1242,"y":844,"w":124,"h":67,"offX":115,"offY":242,"sourceW":360,"sourceH":375},"daji_00046":{"x":1366,"y":844,"w":122,"h":65,"offX":116,"offY":244,"sourceW":360,"sourceH":375},"daji_00047":{"x":0,"y":935,"w":122,"h":65,"offX":116,"offY":243,"sourceW":360,"sourceH":375},"daji_00048":{"x":122,"y":935,"w":122,"h":65,"offX":116,"offY":243,"sourceW":360,"sourceH":375},"daji_00049":{"x":244,"y":935,"w":122,"h":59,"offX":116,"offY":246,"sourceW":360,"sourceH":375},"daji_00050":{"x":366,"y":935,"w":116,"h":59,"offX":116,"offY":246,"sourceW":360,"sourceH":375},"daji_00051":{"x":482,"y":935,"w":114,"h":59,"offX":118,"offY":246,"sourceW":360,"sourceH":375},"daji_00052":{"x":596,"y":935,"w":112,"h":55,"offX":117,"offY":247,"sourceW":360,"sourceH":375},"daji_00053":{"x":708,"y":935,"w":90,"h":47,"offX":135,"offY":247,"sourceW":360,"sourceH":375},"daji_00054":{"x":798,"y":935,"w":88,"h":45,"offX":135,"offY":249,"sourceW":360,"sourceH":375},"daji_00055":{"x":886,"y":935,"w":88,"h":45,"offX":135,"offY":249,"sourceW":360,"sourceH":375},"daji_00056":{"x":974,"y":935,"w":82,"h":41,"offX":140,"offY":251,"sourceW":360,"sourceH":375},"daji_00057":{"x":1056,"y":935,"w":82,"h":41,"offX":140,"offY":251,"sourceW":360,"sourceH":375},"daji_00058":{"x":1138,"y":935,"w":78,"h":41,"offX":144,"offY":251,"sourceW":360,"sourceH":375},"daji_00059":{"x":1216,"y":935,"w":76,"h":41,"offX":143,"offY":251,"sourceW":360,"sourceH":375},"daji_00060":{"x":1292,"y":935,"w":68,"h":37,"offX":148,"offY":251,"sourceW":360,"sourceH":375},"daji_00061":{"x":1360,"y":935,"w":46,"h":33,"offX":155,"offY":251,"sourceW":360,"sourceH":375}}}