{"file":"stand_5.png","frames":{"5_01":{"x":198,"y":194,"w":28,"h":46,"offX":7,"offY":7,"sourceW":54,"sourceH":54},"5_02":{"x":168,"y":190,"w":28,"h":46,"offX":7,"offY":7,"sourceW":54,"sourceH":54},"5_03":{"x":108,"y":192,"w":28,"h":46,"offX":7,"offY":7,"sourceW":54,"sourceH":54},"5_04":{"x":138,"y":190,"w":28,"h":46,"offX":7,"offY":7,"sourceW":54,"sourceH":54},"5_05":{"x":200,"y":146,"w":28,"h":46,"offX":7,"offY":7,"sourceW":54,"sourceH":54},"5_06":{"x":170,"y":142,"w":28,"h":46,"offX":6,"offY":7,"sourceW":54,"sourceH":54},"5_07":{"x":108,"y":96,"w":30,"h":46,"offX":4,"offY":7,"sourceW":54,"sourceH":54},"5_08":{"x":74,"y":192,"w":32,"h":46,"offX":1,"offY":7,"sourceW":54,"sourceH":54},"5_09":{"x":38,"y":2,"w":34,"h":46,"offX":0,"offY":7,"sourceW":54,"sourceH":54},"5_10":{"x":74,"y":144,"w":32,"h":46,"offX":0,"offY":8,"sourceW":54,"sourceH":54},"5_11":{"x":2,"y":194,"w":34,"h":46,"offX":0,"offY":8,"sourceW":54,"sourceH":54},"5_12":{"x":2,"y":146,"w":34,"h":46,"offX":0,"offY":8,"sourceW":54,"sourceH":54},"5_13":{"x":2,"y":98,"w":34,"h":46,"offX":0,"offY":8,"sourceW":54,"sourceH":54},"5_14":{"x":2,"y":50,"w":34,"h":46,"offX":0,"offY":8,"sourceW":54,"sourceH":54},"5_15":{"x":2,"y":2,"w":34,"h":46,"offX":0,"offY":8,"sourceW":54,"sourceH":54},"5_16":{"x":74,"y":2,"w":34,"h":44,"offX":0,"offY":9,"sourceW":54,"sourceH":54},"5_17":{"x":38,"y":188,"w":34,"h":44,"offX":0,"offY":9,"sourceW":54,"sourceH":54},"5_18":{"x":38,"y":142,"w":34,"h":44,"offX":0,"offY":9,"sourceW":54,"sourceH":54},"5_19":{"x":38,"y":96,"w":34,"h":44,"offX":0,"offY":8,"sourceW":54,"sourceH":54},"5_20":{"x":38,"y":50,"w":34,"h":44,"offX":0,"offY":8,"sourceW":54,"sourceH":54},"5_21":{"x":176,"y":50,"w":32,"h":44,"offX":0,"offY":8,"sourceW":54,"sourceH":54},"5_22":{"x":74,"y":96,"w":32,"h":46,"offX":0,"offY":7,"sourceW":54,"sourceH":54},"5_23":{"x":178,"y":2,"w":32,"h":46,"offX":0,"offY":7,"sourceW":54,"sourceH":54},"5_24":{"x":144,"y":2,"w":32,"h":46,"offX":0,"offY":7,"sourceW":54,"sourceH":54},"5_25":{"x":74,"y":48,"w":32,"h":46,"offX":0,"offY":7,"sourceW":54,"sourceH":54},"5_26":{"x":142,"y":50,"w":32,"h":44,"offX":0,"offY":8,"sourceW":54,"sourceH":54},"5_27":{"x":108,"y":50,"w":32,"h":44,"offX":0,"offY":8,"sourceW":54,"sourceH":54},"5_28":{"x":110,"y":2,"w":32,"h":46,"offX":0,"offY":7,"sourceW":54,"sourceH":54},"5_29":{"x":172,"y":96,"w":30,"h":44,"offX":3,"offY":8,"sourceW":54,"sourceH":54},"5_30":{"x":140,"y":96,"w":30,"h":44,"offX":3,"offY":8,"sourceW":54,"sourceH":54},"5_31":{"x":210,"y":50,"w":30,"h":46,"offX":4,"offY":7,"sourceW":54,"sourceH":54},"5_32":{"x":212,"y":2,"w":30,"h":46,"offX":4,"offY":7,"sourceW":54,"sourceH":54},"5_33":{"x":108,"y":144,"w":28,"h":46,"offX":6,"offY":7,"sourceW":54,"sourceH":54},"5_34":{"x":140,"y":142,"w":28,"h":46,"offX":7,"offY":7,"sourceW":54,"sourceH":54},"5_35":{"x":204,"y":98,"w":28,"h":46,"offX":7,"offY":7,"sourceW":54,"sourceH":54}}}