{"frameRate":24,"name":"hundun2_effect_beishu","version":"5.5","compatibleVersion":"5.5","armature":[{"type":"Armature","frameRate":24,"name":"hundun2_effect_beishu","aabb":{"x":-128,"y":-128,"width":256,"height":256},"bone":[{"name":"root"},{"length":2,"name":"x1","parent":"root"},{"name":"3333","parent":"root","transform":{"x":-34.0539,"y":10.0247,"scX":0.6,"scY":0.6}},{"name":"33331","parent":"root","transform":{"x":17.6932,"y":35.8488,"scX":0.4,"scY":0.4}},{"name":"333311","parent":"root","transform":{"x":51.6957,"y":40.4134,"scX":0.2,"scY":0.2}},{"name":"3333111","parent":"root","transform":{"x":6.7748,"y":54.4156,"scX":0.35,"scY":0.35}},{"name":"33331111","parent":"root","transform":{"x":1.5105,"y":18.9019,"scX":0.7,"scY":0.7}},{"name":"333311111","parent":"root","transform":{"x":-7.8958,"y":40.6451,"scX":0.5,"scY":0.5}},{"name":"3333111111","parent":"root","transform":{"x":23.0226,"y":9.1226,"scX":0.5,"scY":0.5}},{"name":"33331111111","parent":"root","transform":{"x":-52.0644,"y":43.3032,"scX":0.5,"scY":0.5}},{"name":"333311111111","parent":"root","transform":{"x":56.4566,"y":7.5392,"scX":0.5,"scY":0.5}},{"name":"3333111111111","parent":"root","transform":{"x":-51.9793,"y":7.5392,"scX":0.5,"scY":0.5}},{"name":"33331111111111","parent":"root","transform":{"x":36.0451,"y":17.7449,"scX":0.5,"scY":0.5}},{"name":"x11","parent":"x1"}],"slot":[{"blendMode":"add","name":"xx1111111","parent":"33331111111"},{"blendMode":"add","name":"xx111111","parent":"3333111111"},{"blendMode":"add","name":"ciguang122_00000","parent":"x1"},{"blendMode":"add","name":"xx11","parent":"333311"},{"blendMode":"add","name":"xx111","parent":"3333111"},{"name":"x1","parent":"x1"},{"blendMode":"add","name":"x111","parent":"x1","color":{"gM":56,"bM":0}},{"blendMode":"add","name":"x11","parent":"x11"},{"blendMode":"add","name":"xx","parent":"3333"},{"blendMode":"add","name":"xx1","parent":"33331"},{"blendMode":"add","name":"xx1111","parent":"33331111"},{"blendMode":"add","name":"xx11111","parent":"333311111"},{"blendMode":"add","name":"xx11111111","parent":"333311111111"},{"blendMode":"add","name":"xx111111111","parent":"3333111111111"},{"blendMode":"add","name":"xx1111111111","parent":"33331111111111"}],"skin":[{"slot":[{"name":"xx","display":[{"name":"xx"}]},{"name":"xx111111","display":[{"name":"xx"}]},{"name":"xx1111111","display":[{"name":"xx","transform":{"x":0.13,"y":-0.63}}]},{"name":"xx111","display":[{"name":"xx"}]},{"name":"ciguang122_00000","display":[{"name":"ciguang122_00000","transform":{"skX":-46,"skY":-46}}]},{"name":"x11","display":[{"name":"x1","path":"1_00000"}]},{"name":"xx11","display":[{"name":"xx"}]},{"name":"xx111111111","display":[{"name":"xx"}]},{"name":"xx1111","display":[{"name":"xx"}]},{"name":"xx11111111","display":[{"name":"xx"}]},{"name":"xx11111","display":[{"name":"xx"}]},{"name":"x1","display":[{"name":"x1"}]},{"name":"xx1","display":[{"name":"xx"}]},{"name":"x111","display":[{"name":"x11","transform":{"scX":1.4,"scY":1.15}}]},{"name":"xx1111111111","display":[{"name":"xx"}]}]}],"animation":[{"duration":30,"playTimes":0,"name":"show","bone":[{"name":"x1","scaleFrame":[{"duration":15,"curve":[0.5,0,0.5,1]},{"duration":15,"curve":[0.5,0,0.5,1],"x":1.05,"y":1.05},{"duration":0}]},{"name":"3333","translateFrame":[{"duration":24,"curve":[0.5,0,0.5,1]},{"duration":6,"y":-50.98}],"rotateFrame":[{"duration":24,"curve":[0.5,0,0.5,1]},{"duration":6,"rotate":70}],"scaleFrame":[{"duration":9,"curve":[0.5,0,0.5,1],"x":0.02,"y":0.02},{"duration":15,"curve":[0.5,0,0.5,1],"x":0.83,"y":0.83},{"duration":6,"x":0.02,"y":0.02}]},{"name":"33331","translateFrame":[{"duration":28,"curve":[0.5,0,0.5,1]},{"duration":2,"y":-50.98}],"rotateFrame":[{"duration":28,"curve":[0.5,0,0.5,1]},{"duration":2,"rotate":177}],"scaleFrame":[{"duration":14,"curve":[0.5,0,0.5,1],"x":0.02,"y":0.02},{"duration":14,"curve":[0.5,0,0.5,1],"x":0.83,"y":0.83},{"duration":2,"x":0.02,"y":0.02}]},{"name":"333311","translateFrame":[{"duration":3,"curve":[0.5,0,0.5,1]},{"duration":27,"curve":[0.5,0,0.5,1]},{"duration":0,"y":-50.98}],"rotateFrame":[{"duration":3,"curve":[0.5,0,0.5,1]},{"duration":27,"curve":[0.5,0,0.5,1]},{"duration":0,"rotate":127}],"scaleFrame":[{"duration":3,"curve":[0.5,0,0.5,1],"x":0.02,"y":0.02},{"duration":13,"curve":[0.5,0,0.5,1],"x":0.02,"y":0.02},{"duration":14,"curve":[0.5,0,0.5,1],"x":0.83,"y":0.83},{"duration":0,"x":0.02,"y":0.02}]},{"name":"3333111","translateFrame":[{"duration":16,"curve":[0.5,0,0.5,1]},{"duration":14,"y":-50.98}],"rotateFrame":[{"duration":16,"curve":[0.5,0,0.5,1]},{"duration":14,"rotate":132}],"scaleFrame":[{"duration":8,"curve":[0.5,0,0.5,1],"x":0.02,"y":0.02},{"duration":8,"curve":[0.5,0,0.5,1],"x":0.83,"y":0.83},{"duration":14,"x":0.02,"y":0.02}]},{"name":"33331111","translateFrame":[{"duration":5,"curve":[0.5,0,0.5,1]},{"duration":19,"curve":[0.5,0,0.5,1]},{"duration":6,"curve":[0.5,0,0.5,1],"y":-42.32},{"duration":0,"y":-50.98}],"rotateFrame":[{"duration":5,"curve":[0.5,0,0.5,1]},{"duration":25,"curve":[0.5,0,0.5,1]},{"duration":0,"rotate":129}],"scaleFrame":[{"duration":5,"curve":[0.5,0,0.5,1],"x":0.02,"y":0.02},{"duration":13,"curve":[0.5,0,0.5,1],"x":0.02,"y":0.02},{"duration":12,"curve":[0.5,0,0.5,1],"x":0.83,"y":0.83},{"duration":0,"x":0.02,"y":0.02}]},{"name":"333311111","translateFrame":[{"duration":8,"curve":[0.5,0,0.5,1]},{"duration":22,"curve":[0.5,0,0.5,1]},{"duration":0,"y":-50.98}],"rotateFrame":[{"duration":8,"curve":[0.5,0,0.5,1]},{"duration":22,"curve":[0.5,0,0.5,1]},{"duration":0,"rotate":160}],"scaleFrame":[{"duration":8,"curve":[0.5,0,0.5,1],"x":0.02,"y":0.02},{"duration":11,"curve":[0.5,0,0.5,1],"x":0.02,"y":0.02},{"duration":11,"curve":[0.5,0,0.5,1],"x":0.83,"y":0.83},{"duration":0,"x":0.02,"y":0.02}]},{"name":"3333111111","translateFrame":[{"duration":4,"curve":[0.5,0,0.5,1]},{"duration":22,"curve":[0.5,0,0.5,1]},{"duration":4,"y":-50.98}],"rotateFrame":[{"duration":4,"curve":[0.5,0,0.5,1]},{"duration":22,"curve":[0.5,0,0.5,1]},{"duration":4,"rotate":167}],"scaleFrame":[{"duration":4,"curve":[0.5,0,0.5,1],"x":0.02,"y":0.02},{"duration":11,"curve":[0.5,0,0.5,1],"x":0.02,"y":0.02},{"duration":11,"curve":[0.5,0,0.5,1],"x":0.83,"y":0.83},{"duration":4,"x":0.02,"y":0.02}]},{"name":"33331111111","translateFrame":[{"duration":10,"curve":[0.5,0,0.5,1]},{"duration":20,"curve":[0.5,0,0.5,1]},{"duration":0,"y":-50.98}],"rotateFrame":[{"duration":10,"curve":[0.5,0,0.5,1]},{"duration":20,"curve":[0.5,0,0.5,1]},{"duration":0,"rotate":180}],"scaleFrame":[{"duration":10,"curve":[0.5,0,0.5,1],"x":0.02,"y":0.02},{"duration":10,"curve":[0.5,0,0.5,1],"x":0.02,"y":0.02},{"duration":10,"curve":[0.5,0,0.5,1],"x":0.83,"y":0.83},{"duration":0,"x":0.02,"y":0.02}]},{"name":"333311111111","translateFrame":[{"duration":4,"curve":[0.5,0,0.5,1]},{"duration":16,"curve":[0.5,0,0.5,1]},{"duration":10,"y":-50.98}],"rotateFrame":[{"duration":4,"curve":[0.5,0,0.5,1]},{"duration":16,"curve":[0.5,0,0.5,1]},{"duration":10,"rotate":169}],"scaleFrame":[{"duration":4,"curve":[0.5,0,0.5,1],"x":0.02,"y":0.02},{"duration":7,"curve":[0.5,0,0.5,1],"x":0.02,"y":0.02},{"duration":9,"curve":[0.5,0,0.5,1],"x":0.83,"y":0.83},{"duration":10,"x":0.02,"y":0.02}]},{"name":"x11","scaleFrame":[{"duration":15,"curve":[0.5,0,0.5,1]},{"duration":15,"curve":[0.5,0,0.5,1],"x":1.1,"y":1.1},{"duration":0}]},{"name":"3333111111111","translateFrame":[{"duration":13,"curve":[0.5,0,0.5,1]},{"duration":16,"curve":[0.5,0,0.5,1]},{"y":-50.98}],"rotateFrame":[{"duration":13,"curve":[0.5,0,0.5,1]},{"duration":16,"curve":[0.5,0,0.5,1]},{"rotate":169}],"scaleFrame":[{"duration":13,"curve":[0.5,0,0.5,1],"x":0.02,"y":0.02},{"duration":7,"curve":[0.5,0,0.5,1],"x":0.02,"y":0.02},{"duration":9,"curve":[0.5,0,0.5,1],"x":0.83,"y":0.83},{"x":0.02,"y":0.02}]},{"name":"33331111111111","translateFrame":[{"duration":9,"curve":[0.5,0,0.5,1]},{"duration":16,"curve":[0.5,0,0.5,1]},{"duration":5,"y":-50.98}],"rotateFrame":[{"duration":9,"curve":[0.5,0,0.5,1]},{"duration":16,"curve":[0.5,0,0.5,1]},{"duration":5,"rotate":169}],"scaleFrame":[{"duration":9,"curve":[0.5,0,0.5,1],"x":0.02,"y":0.02},{"duration":7,"curve":[0.5,0,0.5,1],"x":0.02,"y":0.02},{"duration":9,"curve":[0.5,0,0.5,1],"x":0.83,"y":0.83},{"duration":5,"x":0.02,"y":0.02}]}],"slot":[{"name":"x11","colorFrame":[{"duration":15,"curve":[0.5,0,0.5,1],"value":{"aM":50}},{"duration":15,"curve":[0.5,0,0.5,1]},{"duration":0,"value":{"aM":50}}]},{"name":"x111","colorFrame":[{"duration":15,"curve":[0.5,0,0.5,1],"value":{"aM":0,"gM":56,"bM":0}},{"duration":15,"curve":[0.5,0,0.5,1],"value":{"aM":70,"gM":56,"bM":0}},{"duration":0,"value":{"aM":0,"gM":56,"bM":0}}]},{"name":"ciguang122_00000","colorFrame":[{"duration":15,"tweenEasing":0,"value":{"aM":0}},{"duration":15,"tweenEasing":0,"value":{"aM":20}},{"duration":0,"value":{"aM":0}}]}]}],"defaultActions":[{"gotoAndPlay":"show"}]}]}