{"file":"showBoss_up_1.png","frames":{"s_00000":{"x":526,"y":284,"w":1,"h":1,"offX":0,"offY":0,"sourceW":682,"sourceH":384},"s_00001":{"x":1756,"y":2,"w":24,"h":44,"offX":332,"offY":116,"sourceW":682,"sourceH":384},"s_00002":{"x":498,"y":284,"w":26,"h":44,"offX":331,"offY":116,"sourceW":682,"sourceH":384},"s_00003":{"x":470,"y":284,"w":26,"h":44,"offX":331,"offY":116,"sourceW":682,"sourceH":384},"s_00004":{"x":844,"y":714,"w":132,"h":72,"offX":225,"offY":116,"sourceW":682,"sourceH":384},"s_00005":{"x":844,"y":556,"w":134,"h":156,"offX":223,"offY":115,"sourceW":682,"sourceH":384},"s_00006":{"x":1626,"y":1050,"w":162,"h":168,"offX":195,"offY":115,"sourceW":682,"sourceH":384},"s_00007":{"x":1530,"y":172,"w":162,"h":168,"offX":195,"offY":116,"sourceW":682,"sourceH":384},"s_00008":{"x":1530,"y":2,"w":224,"h":168,"offX":196,"offY":116,"sourceW":682,"sourceH":384},"s_00009":{"x":1148,"y":1792,"w":280,"h":168,"offX":196,"offY":115,"sourceW":682,"sourceH":384},"s_00010":{"x":1350,"y":1582,"w":278,"h":168,"offX":197,"offY":115,"sourceW":682,"sourceH":384},"s_00011":{"x":1430,"y":1752,"w":276,"h":168,"offX":198,"offY":115,"sourceW":682,"sourceH":384},"s_00012":{"x":2,"y":1836,"w":272,"h":166,"offX":201,"offY":116,"sourceW":682,"sourceH":384},"s_00013":{"x":548,"y":1836,"w":270,"h":166,"offX":202,"offY":116,"sourceW":682,"sourceH":384},"s_00014":{"x":276,"y":1836,"w":270,"h":166,"offX":204,"offY":116,"sourceW":682,"sourceH":384},"s_00015":{"x":1524,"y":342,"w":270,"h":166,"offX":205,"offY":116,"sourceW":682,"sourceH":384},"s_00016":{"x":980,"y":498,"w":410,"h":222,"offX":138,"offY":104,"sourceW":682,"sourceH":384},"s_00017":{"x":538,"y":2,"w":528,"h":304,"offX":81,"offY":80,"sourceW":682,"sourceH":384},"s_00018":{"x":2,"y":2,"w":534,"h":280,"offX":58,"offY":80,"sourceW":682,"sourceH":384},"s_00019":{"x":2,"y":536,"w":442,"h":238,"offX":122,"offY":99,"sourceW":682,"sourceH":384},"s_00020":{"x":1068,"y":252,"w":454,"h":244,"offX":116,"offY":98,"sourceW":682,"sourceH":384},"s_00021":{"x":1068,"y":2,"w":460,"h":248,"offX":113,"offY":97,"sourceW":682,"sourceH":384},"s_00022":{"x":2,"y":284,"w":466,"h":250,"offX":110,"offY":96,"sourceW":682,"sourceH":384},"s_00023":{"x":526,"y":308,"w":452,"h":246,"offX":117,"offY":97,"sourceW":682,"sourceH":384},"s_00024":{"x":446,"y":736,"w":396,"h":178,"offX":146,"offY":107,"sourceW":682,"sourceH":384},"s_00025":{"x":446,"y":556,"w":396,"h":178,"offX":145,"offY":107,"sourceW":682,"sourceH":384},"s_00026":{"x":1392,"y":692,"w":396,"h":178,"offX":145,"offY":107,"sourceW":682,"sourceH":384},"s_00027":{"x":1392,"y":510,"w":396,"h":180,"offX":145,"offY":106,"sourceW":682,"sourceH":384},"s_00028":{"x":978,"y":722,"w":394,"h":180,"offX":147,"offY":106,"sourceW":682,"sourceH":384},"s_00029":{"x":1374,"y":872,"w":392,"h":176,"offX":149,"offY":108,"sourceW":682,"sourceH":384},"s_00030":{"x":394,"y":916,"w":390,"h":176,"offX":151,"offY":108,"sourceW":682,"sourceH":384},"s_00031":{"x":844,"y":904,"w":390,"h":176,"offX":151,"offY":108,"sourceW":682,"sourceH":384},"s_00032":{"x":1236,"y":1050,"w":388,"h":176,"offX":152,"offY":108,"sourceW":682,"sourceH":384},"s_00033":{"x":2,"y":776,"w":390,"h":176,"offX":150,"offY":108,"sourceW":682,"sourceH":384},"s_00034":{"x":2,"y":954,"w":388,"h":176,"offX":150,"offY":108,"sourceW":682,"sourceH":384},"s_00035":{"x":1174,"y":1228,"w":386,"h":176,"offX":150,"offY":108,"sourceW":682,"sourceH":384},"s_00036":{"x":2,"y":1132,"w":386,"h":176,"offX":150,"offY":108,"sourceW":682,"sourceH":384},"s_00037":{"x":786,"y":1082,"w":386,"h":178,"offX":150,"offY":107,"sourceW":682,"sourceH":384},"s_00038":{"x":392,"y":1094,"w":386,"h":176,"offX":149,"offY":109,"sourceW":682,"sourceH":384},"s_00039":{"x":2,"y":1310,"w":384,"h":172,"offX":150,"offY":112,"sourceW":682,"sourceH":384},"s_00040":{"x":780,"y":1262,"w":384,"h":176,"offX":150,"offY":108,"sourceW":682,"sourceH":384},"s_00041":{"x":390,"y":1272,"w":384,"h":174,"offX":150,"offY":109,"sourceW":682,"sourceH":384},"s_00042":{"x":1166,"y":1406,"w":380,"h":174,"offX":152,"offY":109,"sourceW":682,"sourceH":384},"s_00043":{"x":776,"y":1440,"w":376,"h":174,"offX":152,"offY":109,"sourceW":682,"sourceH":384},"s_00044":{"x":388,"y":1448,"w":366,"h":174,"offX":156,"offY":109,"sourceW":682,"sourceH":384},"s_00045":{"x":2,"y":1484,"w":354,"h":174,"offX":165,"offY":109,"sourceW":682,"sourceH":384},"s_00046":{"x":2,"y":1660,"w":350,"h":174,"offX":168,"offY":108,"sourceW":682,"sourceH":384},"s_00047":{"x":354,"y":1660,"w":338,"h":174,"offX":178,"offY":108,"sourceW":682,"sourceH":384},"s_00048":{"x":694,"y":1624,"w":330,"h":174,"offX":179,"offY":108,"sourceW":682,"sourceH":384},"s_00049":{"x":820,"y":1800,"w":326,"h":174,"offX":179,"offY":108,"sourceW":682,"sourceH":384},"s_00050":{"x":1026,"y":1616,"w":322,"h":174,"offX":178,"offY":108,"sourceW":682,"sourceH":384}}}