{"file":"move_1.png","frames":{"walk0016":{"x":0,"y":0,"w":208,"h":182,"offX":144,"offY":106,"sourceW":472,"sourceH":472},"walk0008":{"x":208,"y":0,"w":212,"h":180,"offX":145,"offY":98,"sourceW":472,"sourceH":472},"walk0020":{"x":420,"y":0,"w":212,"h":180,"offX":143,"offY":103,"sourceW":472,"sourceH":472},"walk0018":{"x":632,"y":0,"w":210,"h":182,"offX":143,"offY":106,"sourceW":472,"sourceH":472},"walk0014":{"x":842,"y":0,"w":208,"h":184,"offX":145,"offY":104,"sourceW":472,"sourceH":472},"walk0022":{"x":1050,"y":0,"w":214,"h":180,"offX":143,"offY":99,"sourceW":472,"sourceH":472},"walk0006":{"x":1264,"y":0,"w":212,"h":182,"offX":145,"offY":101,"sourceW":472,"sourceH":472},"walk0000":{"x":1476,"y":0,"w":212,"h":184,"offX":144,"offY":104,"sourceW":472,"sourceH":472},"walk0028":{"x":0,"y":184,"w":212,"h":184,"offX":144,"offY":104,"sourceW":472,"sourceH":472},"walk0012":{"x":212,"y":184,"w":210,"h":186,"offX":145,"offY":99,"sourceW":472,"sourceH":472},"walk0024":{"x":422,"y":184,"w":214,"h":184,"offX":144,"offY":97,"sourceW":472,"sourceH":472},"walk0026":{"x":636,"y":184,"w":212,"h":186,"offX":145,"offY":99,"sourceW":472,"sourceH":472},"walk0004":{"x":848,"y":184,"w":212,"h":186,"offX":144,"offY":102,"sourceW":472,"sourceH":472},"walk0002":{"x":1060,"y":184,"w":212,"h":186,"offX":144,"offY":103,"sourceW":472,"sourceH":472},"walk0010":{"x":1272,"y":184,"w":212,"h":186,"offX":145,"offY":96,"sourceW":472,"sourceH":472}}}