{"file":"move_4.png","frames":{"4_01":{"x":2,"y":226,"w":202,"h":218,"offX":271,"offY":215,"sourceW":726,"sourceH":726},"4_02":{"x":2,"y":2,"w":204,"h":222,"offX":272,"offY":222,"sourceW":726,"sourceH":726},"4_03":{"x":206,"y":226,"w":198,"h":218,"offX":270,"offY":224,"sourceW":726,"sourceH":726},"4_04":{"x":406,"y":220,"w":182,"h":214,"offX":278,"offY":225,"sourceW":726,"sourceH":726},"4_05":{"x":762,"y":216,"w":164,"h":212,"offX":288,"offY":226,"sourceW":726,"sourceH":726},"4_06":{"x":928,"y":216,"w":154,"h":212,"offX":291,"offY":225,"sourceW":726,"sourceH":726},"4_07":{"x":966,"y":2,"w":152,"h":212,"offX":287,"offY":227,"sourceW":726,"sourceH":726},"4_08":{"x":1120,"y":2,"w":150,"h":212,"offX":283,"offY":229,"sourceW":726,"sourceH":726},"4_09":{"x":1084,"y":216,"w":150,"h":212,"offX":279,"offY":229,"sourceW":726,"sourceH":726},"4_10":{"x":856,"y":430,"w":150,"h":210,"offX":275,"offY":229,"sourceW":726,"sourceH":726},"4_11":{"x":810,"y":2,"w":154,"h":212,"offX":273,"offY":229,"sourceW":726,"sourceH":726},"4_12":{"x":644,"y":2,"w":164,"h":212,"offX":270,"offY":228,"sourceW":726,"sourceH":726},"4_13":{"x":590,"y":216,"w":170,"h":212,"offX":268,"offY":225,"sourceW":726,"sourceH":726},"4_14":{"x":678,"y":430,"w":176,"h":210,"offX":264,"offY":222,"sourceW":726,"sourceH":726},"4_15":{"x":1008,"y":430,"w":186,"h":208,"offX":258,"offY":219,"sourceW":726,"sourceH":726},"4_16":{"x":1420,"y":418,"w":198,"h":200,"offX":254,"offY":222,"sourceW":726,"sourceH":726},"4_17":{"x":1272,"y":2,"w":200,"h":200,"offX":255,"offY":221,"sourceW":726,"sourceH":726},"4_18":{"x":1236,"y":216,"w":204,"h":200,"offX":255,"offY":218,"sourceW":726,"sourceH":726},"4_19":{"x":1668,"y":200,"w":206,"h":198,"offX":254,"offY":217,"sourceW":726,"sourceH":726},"4_20":{"x":1668,"y":2,"w":210,"h":196,"offX":253,"offY":217,"sourceW":726,"sourceH":726},"4_21":{"x":1620,"y":404,"w":218,"h":196,"offX":251,"offY":215,"sourceW":726,"sourceH":726},"4_22":{"x":2,"y":446,"w":224,"h":194,"offX":249,"offY":215,"sourceW":726,"sourceH":726},"4_23":{"x":228,"y":446,"w":222,"h":194,"offX":250,"offY":215,"sourceW":726,"sourceH":726},"4_24":{"x":1442,"y":204,"w":224,"h":198,"offX":252,"offY":213,"sourceW":726,"sourceH":726},"4_25":{"x":452,"y":436,"w":224,"h":202,"offX":257,"offY":214,"sourceW":726,"sourceH":726},"4_26":{"x":1196,"y":430,"w":222,"h":206,"offX":263,"offY":214,"sourceW":726,"sourceH":726},"4_27":{"x":424,"y":2,"w":218,"h":212,"offX":265,"offY":213,"sourceW":726,"sourceH":726},"4_28":{"x":208,"y":2,"w":214,"h":216,"offX":266,"offY":214,"sourceW":726,"sourceH":726}}}