{"file":"stand_3.png","frames":{"1_00":{"x":0,"y":0,"w":158,"h":262,"offX":116,"offY":22,"sourceW":450,"sourceH":450},"1_02":{"x":158,"y":0,"w":152,"h":258,"offX":121,"offY":26,"sourceW":450,"sourceH":450},"1_04":{"x":310,"y":0,"w":150,"h":258,"offX":123,"offY":27,"sourceW":450,"sourceH":450},"1_06":{"x":0,"y":262,"w":150,"h":258,"offX":122,"offY":27,"sourceW":450,"sourceH":450},"1_08":{"x":150,"y":262,"w":150,"h":258,"offX":122,"offY":27,"sourceW":450,"sourceH":450},"1_10":{"x":300,"y":262,"w":148,"h":258,"offX":123,"offY":27,"sourceW":450,"sourceH":450},"1_12":{"x":0,"y":520,"w":150,"h":258,"offX":121,"offY":27,"sourceW":450,"sourceH":450},"1_14":{"x":150,"y":520,"w":150,"h":258,"offX":121,"offY":28,"sourceW":450,"sourceH":450},"1_16":{"x":300,"y":520,"w":156,"h":260,"offX":116,"offY":26,"sourceW":450,"sourceH":450},"1_18":{"x":0,"y":780,"w":158,"h":264,"offX":114,"offY":23,"sourceW":450,"sourceH":450},"1_20":{"x":158,"y":780,"w":156,"h":260,"offX":117,"offY":27,"sourceW":450,"sourceH":450},"1_22":{"x":314,"y":780,"w":154,"h":258,"offX":119,"offY":29,"sourceW":450,"sourceH":450},"1_24":{"x":0,"y":1044,"w":156,"h":258,"offX":117,"offY":29,"sourceW":450,"sourceH":450},"1_26":{"x":156,"y":1044,"w":156,"h":258,"offX":117,"offY":29,"sourceW":450,"sourceH":450},"1_28":{"x":312,"y":1044,"w":156,"h":258,"offX":117,"offY":29,"sourceW":450,"sourceH":450},"1_30":{"x":0,"y":1302,"w":156,"h":256,"offX":118,"offY":30,"sourceW":450,"sourceH":450},"1_32":{"x":156,"y":1302,"w":156,"h":258,"offX":117,"offY":28,"sourceW":450,"sourceH":450},"1_34":{"x":312,"y":1302,"w":154,"h":258,"offX":119,"offY":27,"sourceW":450,"sourceH":450},"1_36":{"x":0,"y":1560,"w":156,"h":262,"offX":117,"offY":23,"sourceW":450,"sourceH":450},"1_38":{"x":156,"y":1560,"w":158,"h":264,"offX":116,"offY":21,"sourceW":450,"sourceH":450}}}