[{"client_key":"id"},{"id":900,"sign":"world_boss_rank","name":"世界Boss排名獎勵","type":1,"sender_id":1,"weight_value":0,"content":"恭喜你！在世界Boss圍剿中，傷害排名位於第{%text}名，獎勵將以郵件形式發送到您帳戶上，請注意查收。","award_id":0,"valid_time":432000,"desc":"text=玩家名次"},{"id":901,"sign":"world_boss_kill","name":"世界Boss幸運大獎","type":1,"sender_id":1,"weight_value":0,"content":"恭喜你！在世界Boss圍剿中獲得幸運大獎，獎勵將以郵件形式發送到您帳戶上，請注意查收。","award_id":0,"valid_time":432000},{"id":999,"sign":"invite_rewards","name":"邀請獎勵（被邀請玩家的郵件）","type":1,"sender_id":1,"weight_value":0,"content":"恭喜你！被{%text}成功邀請","award_id":998,"valid_time":432000,"desc":"邀请方玩家名"},{"id":1,"sign":"bag_fill","name":"背包已滿","type":1,"sender_id":1,"weight_value":0,"content":"您的背包已滿，獲得的物品將通過郵件發送到您的帳戶上，請及時收取。","award_id":0,"valid_time":172800},{"id":2,"sign":"shou_chong","name":"首儲","type":1,"sender_id":1,"weight_value":10,"content":"首儲成功，請查收！","award_id":0,"valid_time":172800},{"id":401,"sign":"every_pay","name":"儲值成功","type":1,"sender_id":1,"weight_value":10,"content":"感謝您的儲值！您的儲值已到賬，請注意查收。","award_id":0,"valid_time":432000},{"id":402,"sign":"every_pay_coin","name":"儲值金幣","type":1,"sender_id":1,"weight_value":10,"content":"感謝您的儲值！您儲值的{%text}已到賬，請注意查收。","award_id":0,"valid_time":432000,"desc":"text1=单次储值获得的金币数"},{"id":403,"sign":"every_pay_diamond","name":"儲值鑽石","type":1,"sender_id":1,"weight_value":10,"content":"感謝您的儲值！您儲值的{%text}鑽石已到賬，請注意查收。","award_id":0,"valid_time":432000,"desc":"text1=单次储值获得的钻石数"},{"id":461,"sign":"impact_activity_ranking","name":"沖榜排名獎勵","type":1,"sender_id":1,"weight_value":10,"content":"恭喜你！在開服沖榜活動中位於{%text}的第{%text}名，獎勵將以郵件形式發送到您帳戶上，請注意查收。","award_id":0,"valid_time":432000,"desc":"text1=榜单类型，读取open_service_impact_activity表中的activity_name字段;text2=玩家名次"},{"id":1001,"sign":"gm_mail_send","name":"gm獎勵發送","type":2,"sender_id":2,"weight_value":10,"content":"{%text}","award_id":0,"valid_time":0,"desc":"后台gm奖励发送"},{"id":1002,"sign":"gm_platform_mail_send","name":"gm平臺郵件發送","type":2,"sender_id":2,"weight_value":10,"content":"{%text}","award_id":0,"valid_time":0,"desc":"后台gm奖励发送"},{"id":3012,"sign":"hefu_seven_login_award","name":"合服七天登陸獎勵發放","type":1,"sender_id":1,"weight_value":0,"content":"您在合服七天登陸活動中有獎勵尚未領取，獎勵將以郵件形式發送到您帳戶上，請注意查收。","award_id":0,"valid_time":432000},{"id":801,"sign":"mission_either_or","name":"二選一翻倍","type":1,"sender_id":1,"weight_value":7,"content":"您在翻倍玩法中離開，這是您離開後獎勵，請查收！","award_id":0,"valid_time":432000},{"id":802,"sign":"many_people_shishi_mission_mail","name":"組隊時時結算獎勵","type":1,"sender_id":1,"weight_value":7,"content":"您在組隊boss戰鬥中掉線，這是您的贏得的獎勵，請查收","award_id":0,"valid_time":432000},{"id":803,"sign":"many_people_boss_mail","name":"多人boss房主抽傭獎勵","type":1,"sender_id":1,"weight_value":7,"content":"您在多人boss戰鬥中擔任房主時掉線，您的抽傭獎勵已發送到您的郵箱，請查收","award_id":0,"valid_time":432000},{"id":804,"sign":"many_people_boss_mission_mail","name":"多人boss戰鬥排行獎勵","type":1,"sender_id":1,"weight_value":7,"content":"您在多人boss戰鬥中掉線，這是您的排行獎勵，請查收","award_id":0,"valid_time":432000},{"id":805,"sign":"many_people_boss_mission_fail_mail","name":"多人boss戰鬥失敗郵件","type":1,"sender_id":1,"weight_value":7,"content":"您在多人boss戰鬥中掉線，最終戰鬥失敗，沒有獲得獎勵，希望您下次再接再厲！","award_id":0,"valid_time":432000},{"id":821,"sign":"guess_boss_balance","name":"六選一中獎","type":1,"sender_id":1,"weight_value":7,"content":"角鬥場最終勝利選手為{%text}號，本次獎勵{%text}鑽石！","award_id":0,"valid_time":432000},{"id":822,"sign":"guess_boss_balance1","name":"六選一未中獎","type":1,"sender_id":1,"weight_value":7,"content":"角鬥場最終勝利選手為{%text}號，本次您為中獎！","award_id":0,"valid_time":432000},{"id":831,"sign":"scene_boss_location_death","name":"場景BOSS位置競猜獎勵","type":1,"sender_id":1,"weight_value":7,"content":"恭喜競猜勝利！BOSS死亡位置為{%text}，本次獎勵{%text}鑽石！","award_id":0,"valid_time":432000},{"id":832,"sign":"scene_boss_location_death1","name":"場景BOSS位置未中獎","type":1,"sender_id":1,"weight_value":7,"content":"競猜位置：BOSS死亡位置為{%text}，本次您為中獎！","award_id":0,"valid_time":432000},{"id":841,"sign":"scene_boss_atk_count_death","name":"場景BOSS刀數競猜獎勵","type":1,"sender_id":1,"weight_value":7,"content":"恭喜競猜勝利！BOSS死亡刀數為{%text}，本次獎勵{%text}鑽石！","award_id":0,"valid_time":432000},{"id":842,"sign":"scene_boss_atk_count_death1","name":"場景BOSS刀數未中獎","type":1,"sender_id":1,"weight_value":7,"content":"競猜刀數：BOSS死亡位置為{%text}，本次您為中獎！","award_id":0,"valid_time":432000},{"id":1101,"sign":"shishi_mission_mail","name":"時時boss獎勵","type":1,"sender_id":1,"weight_value":7,"content":"您在彩金BOSS戰鬥中掉線，這是您的排行獎勵，請查收","award_id":0,"valid_time":432000},{"id":1201,"sign":"pagoda_rank_award_mail","name":"爬塔排行榜獎勵郵件","type":1,"sender_id":1,"weight_value":7,"content":"您在爬塔排行榜中位於第{%text}名，這是您的排行獎勵，請查收","award_id":0,"valid_time":432000},{"id":1301,"sign":"mission_brave_one_back","name":"勇敢者副本開啟失敗","type":1,"sender_id":1,"weight_value":7,"content":"","award_id":0,"valid_time":432000},{"id":1302,"sign":"mission_brave_one_win","name":"勇敢者副本勝利","type":1,"sender_id":1,"weight_value":7,"content":"","award_id":0,"valid_time":432000},{"id":1303,"sign":"mission_brave_one_fail","name":"勇敢者副本失敗","type":1,"sender_id":1,"weight_value":7,"content":"","award_id":0,"valid_time":432000},{"id":1400,"sign":"tongxingzheng_mail","name":"通行證郵件","type":1,"sender_id":1,"weight_value":7,"content":"你有通行證獎勵未領取","award_id":0,"valid_time":432000},{"id":1410,"sign":"activity_lei_chong","name":"累計儲值","type":1,"sender_id":1,"weight_value":7,"content":"累計儲值活動已結束，您有未領取獎勵，通過郵箱發送，請查收！","award_id":0,"valid_time":432000},{"id":9999,"sign":"newbie_login_mail","name":"新手登陸郵件","type":1,"sender_id":1,"weight_value":7,"content":"歡迎您來到異世界，遊戲中有問題可聯繫客服！","award_id":0,"valid_time":432000},{"id":99999,"sign":"repair_brics_mail","name":"","type":1,"sender_id":1,"weight_value":7,"content":"貨幣調整，您的|c102{%text}$c金磚轉換成|c102${%text}$c，請查收!","award_id":0,"valid_time":432000},{"id":30001,"sign":"charge_after_refused","name":"重要提醒","type":1,"sender_id":1,"weight_value":7,"content":"您好，檢測到您穀歌退過款，當前儲值金額已補償之前的退款！有疑問請聯繫客服！","award_id":0,"valid_time":432000},{"id":30002,"sign":"trade_after_refused","name":"重要提醒","type":1,"sender_id":1,"weight_value":7,"content":"您好，檢測到您穀歌退過款，暫時無法發起回收！有疑問請聯繫客服！","award_id":0,"valid_time":432000},{"id":30003,"sign":"single_award","name":"匹配場獎勵","type":1,"sender_id":1,"weight_value":7,"content":"恭喜玩家在|c102{%text}獲得第|c102{%text}名，本次獎勵|c102{%text}賞金石","award_id":0,"valid_time":432000,"desc":"匹配场单局获得奖励提前退出或掉线邮件奖励"},{"id":30004,"sign":"ranking_award","name":"匹配場排行獎勵","type":1,"sender_id":1,"weight_value":7,"content":"恭喜玩家在|c102{%text}獲得每日排行第一名，本次獎勵|c102{%text}賞金石","award_id":0,"valid_time":432000,"desc":"匹配场每日排行结算奖励邮件"},{"id":35000,"sign":"lucky_ball","name":"幸運彩球掉線中獎郵件","type":1,"sender_id":1,"weight_value":7,"content":"您好，您的[幾號球]彩球已中獎，由於您在幸運彩球事件中掉線，獎金[中獎金額]通過郵件方式發放，請查收。","award_id":0,"valid_time":432000,"desc":"幸运彩球掉线邮件"},{"id":35001,"sign":"ranking_list1","name":"初級場排名獎勵","type":1,"sender_id":1,"weight_value":7,"content":"恭喜玩家在1v1初級場獲得每日排行第{%text}名，本次獎勵{%text}賞金石","award_id":0,"valid_time":432000},{"id":35002,"sign":"ranking_list2","name":"中級場排名獎勵","type":1,"sender_id":1,"weight_value":7,"content":"恭喜玩家在1v1中級場獲得每日排行第{%text}名，本次獎勵{%text}賞金石","award_id":0,"valid_time":432000},{"id":35003,"sign":"ranking_list3","name":"高級場排名獎勵","type":1,"sender_id":1,"weight_value":7,"content":"恭喜玩家在1v1高級場獲得每日排行第{%text}名，本次獎勵{%text}賞金石","award_id":0,"valid_time":432000},{"id":35004,"sign":"ranking_list4","name":"掉線或者提前退出郵件獎勵","type":1,"sender_id":1,"weight_value":7,"content":"恭喜玩家在1v1初級場獲得第{%text}名，本次獎勵{%text}賞金石","award_id":0,"valid_time":432000,"desc":"1v1单局获得奖励提前退出或掉线邮件奖励"},{"id":35005,"sign":"ranking_list5","name":"掉線或者提前退出郵件獎勵","type":1,"sender_id":1,"weight_value":7,"content":"恭喜玩家在1v1中級場獲得第{%text}名，本次獎勵{%text}賞金石","award_id":0,"valid_time":432000,"desc":"1v1单局获得奖励提前退出或掉线邮件奖励"},{"id":35006,"sign":"ranking_list6","name":"掉線或者提前退出郵件獎勵","type":1,"sender_id":1,"weight_value":7,"content":"恭喜玩家在1v1高級場獲得第{%text}名，本次獎勵{%text}賞金石","award_id":0,"valid_time":432000,"desc":"1v1单局获得奖励提前退出或掉线邮件奖励"},{"id":35007,"sign":"ranking_list7","name":"平手獎勵","type":1,"sender_id":1,"weight_value":7,"content":"恭喜玩家在1v1初級場獲得平手，本次獎勵{%text}賞金石","award_id":0,"valid_time":432000,"desc":"平手奖励"},{"id":35008,"sign":"ranking_list8","name":"平手獎勵","type":1,"sender_id":1,"weight_value":7,"content":"恭喜玩家在1v1中級場獲得平手，本次獎勵{%text}賞金石","award_id":0,"valid_time":432000,"desc":"平手奖励"},{"id":35009,"sign":"ranking_list9","name":"平手獎勵","type":1,"sender_id":1,"weight_value":7,"content":"恭喜玩家在1v1高級場獲得平手，本次獎勵{%text}賞金石","award_id":0,"valid_time":432000,"desc":"平手奖励"},{"id":36000,"sign":"endless_fight1","name":"掉線郵件獎勵","type":1,"sender_id":1,"weight_value":7,"content":"恭喜玩家在無盡對決模式中獲獎，本次獎勵{%text}金幣","award_id":0,"valid_time":432000,"desc":"无尽对决掉线后中奖的邮件奖励"},{"id":36001,"sign":"endless_fight2","name":"掉線郵件獎勵","type":1,"sender_id":1,"weight_value":7,"content":"恭喜玩家在無盡對決模式中獲獎，本次獎勵{%text}賞金石","award_id":0,"valid_time":432000,"desc":"无尽对决掉线后中奖的邮件奖励"},{"id":36100,"sign":"mercedes_list1","name":"掉線郵件獎勵","type":1,"sender_id":1,"weight_value":7,"content":"恭喜玩家在賓士寶馬金幣場中獲獎，本次獎勵{%text}金幣","award_id":0,"valid_time":432000,"desc":"奔驰宝马掉线后中奖的邮件奖励"},{"id":36101,"sign":"mercedes_list2","name":"掉線郵件獎勵","type":1,"sender_id":1,"weight_value":7,"content":"恭喜玩家在賓士寶馬賞金場中獲獎，本次獎勵{%text}賞金石","award_id":0,"valid_time":432000,"desc":"奔驰宝马掉线后中奖的邮件奖励"},{"id":37001,"sign":"growth_battle1","name":"成長大作戰初級場排名獎勵","type":1,"sender_id":1,"weight_value":7,"content":"恭喜玩家在成長大作戰初級場中獲得每日排行第{%text}名，本次獎勵{%text}賞金石","award_id":0,"valid_time":432000},{"id":37002,"sign":"growth_battle2","name":"成長大作戰中級場排名獎勵","type":1,"sender_id":1,"weight_value":7,"content":"恭喜玩家在成長大作戰中級場中獲得每日排行第{%text}名，本次獎勵{%text}賞金石","award_id":0,"valid_time":432000},{"id":37003,"sign":"growth_battle3","name":"成長大作戰高級場排名獎勵","type":1,"sender_id":1,"weight_value":7,"content":"恭喜玩家在成長大作戰高級場中獲得每日排行第{%text}名，本次獎勵{%text}賞金石","award_id":0,"valid_time":432000},{"id":37004,"sign":"growth_battle4","name":"平手獎勵","type":1,"sender_id":1,"weight_value":7,"content":"恭喜玩家在成長大作戰初級場獲得平手，本次獎勵{%text}賞金石","award_id":0,"valid_time":432000},{"id":37005,"sign":"growth_battle5","name":"平手獎勵","type":1,"sender_id":1,"weight_value":7,"content":"恭喜玩家在成長大作戰中級場獲得平手，本次獎勵{%text}賞金石","award_id":0,"valid_time":432000},{"id":37006,"sign":"growth_battle6","name":"平手獎勵","type":1,"sender_id":1,"weight_value":7,"content":"恭喜玩家在成長大作戰高級場獲得平手，本次獎勵{%text}賞金石","award_id":0,"valid_time":432000},{"id":37007,"sign":"growth_battle7","name":"掉線郵件","type":1,"sender_id":1,"weight_value":7,"content":"恭喜玩家在成長大作戰初級場獲得第{%text}名，本次獎勵{%text}賞金石","award_id":0,"valid_time":432000},{"id":37008,"sign":"growth_battle8","name":"掉線郵件","type":1,"sender_id":1,"weight_value":7,"content":"恭喜玩家在成長大作戰中級場獲得第{%text}名，本次獎勵{%text}賞金石","award_id":0,"valid_time":432000},{"id":37009,"sign":"growth_battle9","name":"掉線郵件","type":1,"sender_id":1,"weight_value":7,"content":"恭喜玩家在成長大作戰高級場場獲得第{%text}名，本次獎勵{%text}賞金石","award_id":0,"valid_time":432000}]