{"file":"Κά»χ.png","frames":{"1_00":{"x":0,"y":0,"w":66,"h":66,"offX":95,"offY":90,"sourceW":256,"sourceH":256},"1_01":{"x":66,"y":0,"w":128,"h":120,"offX":65,"offY":62,"sourceW":256,"sourceH":256},"1_02":{"x":194,"y":0,"w":142,"h":144,"offX":61,"offY":45,"sourceW":256,"sourceH":256},"1_03":{"x":336,"y":0,"w":150,"h":150,"offX":55,"offY":43,"sourceW":256,"sourceH":256},"1_04":{"x":486,"y":0,"w":122,"h":134,"offX":65,"offY":55,"sourceW":256,"sourceH":256},"1_05":{"x":608,"y":0,"w":112,"h":134,"offX":73,"offY":57,"sourceW":256,"sourceH":256},"1_06":{"x":720,"y":0,"w":116,"h":126,"offX":72,"offY":62,"sourceW":256,"sourceH":256},"1_07":{"x":836,"y":0,"w":1,"h":1,"offX":0,"offY":0,"sourceW":256,"sourceH":256}}}