{"name":"yuanxing","list":[{"name":"Action1","StartShowTime":10,"LiveSpan":1000,"ShowResource":"","ProcessResource":"yuanxing&dz","DisappearResource":"","FlyEase":"","FlySpeed":0,"Floor":0,"ShockType":0,"IsFollow":1,"PlayTimes":0,"ReferToPosition":0,"SettlementAndViewOffsetX":-7,"SettlementAndViewOffsetY":16,"ViewOffsetH":0,"DirectionPos":0,"DirectionRotation":0,"Direction":0,"FlyDistance":0,"Settlement":-1,"AlphaStartShowTime":0,"AlphaDisappearTime":0,"SoundDelay":0,"Transform":"-1","SkillCellIndex":1,"zIndex":1,"id":1012}]}